pytasking/__init__.py
pytasking/manager.py
pytasking/utilities.py
pytasking/wrappers.py
pytasking-1.2.dist-info/LICENSE
pytasking-1.2.dist-info/METADATA
pytasking-1.2.dist-info/WHEEL
pytasking-1.2.dist-info/top_level.txt
pytasking-1.2.dist-info/RECORD
