Metadata-Version: 2.1
Name: pytasking
Version: 1.2
Summary: A multitasking library for Python 3.5+
Home-page: https://github.com/TokenChingy/pytasking
Author: Jason Zi Feng Lei
Author-email: TokenChingy@gmail.com
License: UNKNOWN
Platform: UNKNOWN
Classifier: Programming Language :: Python :: 3
Classifier: License :: OSI Approved :: MIT License
Classifier: Operating System :: OS Independent
Requires-Python: >=3.5
